{
    "0": [
        {
            "nric": "s9608507i",
            "name": "s9608507i",
            "location": "s9608507i",
            "checkInDateTime": "2022-06-21 15:19:29",
            "checkOutDateTime": "2022-06-21 15:33:16",
            "ID": 0
        }
    ],
    "1": [
        {
            "nric": "s9608507i",
            "name": "s9608507i",
            "location": "s9608507i",
            "checkInDateTime": "2022-06-21 15:32:14",
            "checkOutDateTime": "2022-06-21 15:33:16",
            "ID": 1
        }
    ],
    "2": [
        {
            "nric": "s9608507i",
            "name": "s9608507i-1",
            "location": "bedok",
            "checkInDateTime": "2022-06-21 15:32:55",
            "checkOutDateTime": "2022-06-21 15:33:16",
            "ID": 2
        }
    ],
    "3": [
        {
            "nric": "s9608507i",
            "name": "s9608507i-2",
            "location": "bedok",
            "checkInDateTime": "2022-06-21 15:32:55",
            "checkOutDateTime": "2022-06-21 15:33:16",
            "ID": 3
        }
    ]
}